{
  "id": "qol.combofix",
  "displayName": "QoL Combo Fix",
  "description": "Various bug fixes and Quality of Life for the Quality of Life mod",
  "tags": [
    "QoL",
    "Utility"
  ],
  "urls": [
    {
      "name": "info",
      "url": "https://github.com/SonPamungkas/NOMNOM-qol-combofix/"
    }
  ],
  "authors": [
    "Neutral Observer"
  ],
  "githubOwner": "SonPamungkas",
  "githubRepoName": "NOMNOM-qol-combofix",
  "autoUpdateArtifacts": "True",
  "artifacts": [
    {
      "fileName": "qol.combofix_v1.0.1.zip",
      "version": "1.0.1",
      "category": "release",
      "type": "plugin",
      "gameVersion": "0.33.3",
      "downloadUrl": "https://github.com/SonPamungkas/NOMNOM-qol-combofix/releases/download/v1.0.1/qol.combofix_v1.0.1.zip",
      "hash": "sha256:4b6466637cba7e1efe59c3a972a58a207b7c717a2a4e737c9d07a0caff84e29c",
      "dependencies": [
        {
          "id": "QoL",
          "version": "1.8.0.0"
        }
      ]
    },
    {
      "fileName": "qol.combofix_v1.0.a.zip",
      "version": "1.0.a",
      "category": "release",
      "type": "plugin",
      "gameVersion": "0.33.3",
      "downloadUrl": "https://github.com/SonPamungkas/NOMNOM-qol-combofix/releases/download/v1.0.a/qol.combofix_v1.0.a.zip",
      "hash": "sha256:0627f79136c1b2c4cbc34261ea44a73e43470741849e096fae2e55edae780aa4",
      "dependencies": [
        {
          "id": "QoL",
          "version": "1.8.0.0"
        }
      ]
    },
    {
      "type": "plugin",
      "fileName": "qol.combofix_v1.0.0.zip",
      "downloadUrl": "https://github.com/SonPamungkas/NOMNOM-qol-combofix/releases/download/v1.0.0/qol.combofix_v1.0.0.zip",
      "hash": "sha256:1723906154ec4f59ddf6d87268cc0a8f333f6c1cedb3d30fd3f399c4027c23ce",
      "gameVersion": "0.33.3",
      "version": "1.0.0",
      "category": "Release",
      "dependencies": [
        {
          "id": "QoL",
          "version": "1.8.0.0"
        }
      ]
    }
  ],
  "downloadCount": 307
}
